{
    "short_name": "TillCoin Wallet",
    "name": "TillCoin Wallet",
    "icons": [
        {
            "src": "./assets/img/token.png",
            "type": "image/png",
            "sizes": "500x500",
            "purpose": "any maskable"
        },
        {
            "src": "./assets/img/token.png",
            "type": "image/png",
            "sizes": "500x500",
            "purpose": "any maskable"
        }
    ],
    "start_url": "token.html",
    "background_color": "#1E222D",
    "theme_color": "#1E222D",
    "display": "standalone",
    "orientation": "portrait"
}